quad_filter/__init__.py
quad_filter/filter_2d.py
quad_filter-0.4.dist-info/LICENSE
quad_filter-0.4.dist-info/METADATA
quad_filter-0.4.dist-info/WHEEL
quad_filter-0.4.dist-info/top_level.txt
quad_filter-0.4.dist-info/RECORD
