Metadata-Version: 2.1
Name: quad-filter
Version: 0.4
Summary: Filtering tools for quad trees
Home-page: https://www.gitlab.com/jbrobertson/quad-filter/
Author: JB Robertson
Author-email: jbr@freeshell.org
License: UNKNOWN
Platform: UNKNOWN
Classifier: Programming Language :: Python :: 3
Classifier: License :: OSI Approved :: MIT License
Classifier: Operating System :: OS Independent
Requires-Python: >=3.6
